Workbook

Sheet 使用说明
A1: 蓟州区旅游经济：模型选择与数据预处理工作簿
A2: 用途：完成问题1—3的两套模型方案比较、缺失补全、异常检测、转换处理和数据补充规划。所有假设补全值均与官方观测分列保存，不会伪装成官方实际值。
A4: 关键数据诊断
A5: 年度样本期数 | C5: 游客量原始缺失 | E5: 综合收入原始缺失 | G5: 同比IQR异常年份
A6: =COUNTA(原始年度数据!A4:A19) -> 16 | C6: =COUNTBLANK(原始年度数据!B4:B19) -> 4 | E6: =COUNTBLANK(原始年度数据!F4:F19) -> 4 | G6: ="2020、2022、2023" -> 2020、2022、2023
A8: 结论先行
A9: 问题1主模型 | B9: 分段Gompertz＋疫情干预＋滚动更新 | C9: 原因 | D9: 短样本、趋势明显、必须解释结构冲击
A10: 问题2主模型 | B10: 干预ARIMAX＋阻尼ETS滚动组合 | C10: 原因 | D10: 低参数、可检验、可给95%区间且能利用宏观变量
A11: 问题3主模型 | B11: 动态弹性情景＋LHS Monte Carlo | C11: 原因 | D11: 能把政策语言转为参数区间并直接生成敏感性排序
A12: 不建议作为主模型 | B12: LSTM、Transformer、XGBoost | C12: 原因 | D12: 仅16期年度样本，深度/树模型极易过拟合且难以形成可信区间
A14: 数据文件与复核入口
A15: 文件/入口 | B15: 作用 | C15: 记录数 | D15: 时间范围 | E15: 口径提醒 | F15: 来源 | G15: 获取日期 | H15: 备注
A16: official_annual_summary_2010_2025.csv | B16: 年度优选宽表 | C16: 16 | D16: 2010—2025 | E16: 不替代长表版本信息 | F16: 本地数据目录 | G16: 2026-08-17 | H16: 本工作簿原始年度数据来源
A17: official_tourism_observations_2010_2025.csv | B17: 旅游长表 | C17: 46 | D17: 2010—2025 | E17: 直接收入与综合收入不可拼接 | F17: 本地数据目录 | G17: 2026-08-17 | H17: 含目标值和五年累计值
A18: official_macro_observations_2010_2025.csv | B18: GDP与第三产业长表 | C18: 37 | D18: 2010—2025 | E18: 初值、预计值、年鉴修订值并存 | F18: 本地数据目录 | G18: 2026-08-17 | H18: 优先最终/修订值
A19: official_related_observations_2014_2025.csv | B19: 相关解释变量 | C19: 37 | D19: 2014—2025 | E19: 多数指标覆盖不完整 | F19: 本地数据目录 | G19: 2026-08-17 | H19: 用于候选外生变量筛选
A20: 蓟州区政府数据发布 | B20: 官方补数入口 | F20: https://www.tjjz.gov.cn/zwgk/sjfb/
A21: 天津统计年鉴 | B21: 宏观修订值 | F21: https://stats.tj.gov.cn/tjsj_52032/tjnj/
A22: 天津市文旅局统计信息 | B22: 文旅供给与结构校验 | F22: https://whly.tj.gov.cn/ZWGKYXXGK1640/ZFXXGK5456_1/FDZDGKNR5153/TJXX3610/

Sheet 模型选择
A1: 问题1—3模型方案比较
A2: 选择原则：主方案优先满足短样本稳定性、统计检验和可解释性；创新方案用于不确定性表达、稳健性验证和答辩展示，不以复杂度替代证据。
A4: 小问 | B4: 方案 | C4: 推荐模型 | D4: 核心原理 | E4: 适配性 | F4: 创新点 | G4: 局限性
A5: 问题1 | B5: 方案1｜基础适配（主推荐） | C5: 分段Gompertz增长模型＋疫情干预项＋滚动窗口更新 | D5: Gompertz曲线把旅游经济理解为由较快增长逐步转向容量约束的过程；在疫情年份加入干预项，并在疫情前、冲击期和恢复期允许增长速度发生变化。每获得一个新年度数据就向前滚动窗口重新估计参数，使基准曲线不会长期受早期样本支配。 | E5: 2010—2019年游客量和综合收入整体增长，而2020—2022年存在结构冲击，2023年后又快速恢复。模型参数少、经济含义清楚，适合16期年度短样本，也能满足问题1“简单增长模型＋适用性评价”的要求。 | F5: 不再用一条全时期曲线硬拟合，而是引入变点、疫情干预和滚动更新；估计时按observed、revised、inferred、target等状态设置质量权重，降低低证据数据对曲线的影响。 | G5: 容量上限对样本末端较敏感；2020—2022和2025含假设补全值，可能改变恢复斜率；模型仍主要描述趋势，不能充分解释政策、客源和新业态之间的非线性作用。
A6: 问题1 | B6: 方案2｜创新融合（增强分析） | C6: 质量加权贝叶斯局部线性趋势＋隐马尔可夫状态切换 | D6: 把无法直接观察的真实旅游趋势看成随时间缓慢变化的状态，再用隐马尔可夫链在“常态增长、外部冲击、恢复反弹”三种状态间切换。不同来源的数据设置不同观测误差，最终得到趋势、状态概率及其可信区间。 | E6: 官方数据同时包含修订值、约数、反推值、累计值和目标值，且存在多处缺失。状态空间模型能够自然处理缺失，贝叶斯框架能把证据等级转化为不确定性，状态切换则对应疫情与恢复阶段。 | F6: 将数据来源质量直接写入观测方差，而非把所有数值等权处理；同时输出每年处于不同发展状态的概率，避免人为先固定断点。 | G6: 16个年度样本不足以稳定估计过多转移概率，结果对先验分布敏感；模型解释和实现难度高于分段曲线，适合作为稳健性或答辩亮点，不宜单独承担主结论。
A7: 问题2 | B7: 方案1｜基础适配（主推荐） | C7: 干预ARIMAX＋阻尼ETS的滚动误差加权组合 | D7: ARIMAX利用游客量或收入自身的滞后关系，并加入GDP、第三产业和疫情干预变量解释变化；阻尼ETS负责捕捉平滑但逐步放缓的趋势。通过滚动预测计算两类模型近期误差，误差小的模型获得更高组合权重，再用残差模拟形成95%预测区间。 | E7: 年度样本短且主要目标只有游客量和综合收入，低参数模型比深度学习稳定；宏观解释变量虽不完整但可形成少量核心因子，疫情虚拟变量可以阻止极端年份扭曲长期系数。 | F7: 在经典ARIMAX基础上加入对数变换、口径断点和疫情干预，并让ARIMAX与ETS权重随滚动误差动态变化，而不是固定平均；区间同时传播残差与外生变量情景的不确定性。 | G7: ARIMAX需要给出2026—2030年外生变量路径；GDP与第三产业高度相关，可能产生共线性；验证期较短使组合权重波动，应限制滞后阶数并报告权重敏感性。
A8: 问题2 | B8: 方案2｜创新融合（增强分析） | C8: GM(1,N)小样本先验＋贝叶斯结构时间序列（BSTS）动态融合 | D8: 灰色GM(1,N)先从少量、不完全信息中给出稳定的长期趋势，再把这一趋势作为BSTS的先验或一个候选预测源；BSTS进一步分解局部趋势、外生回归和疫情干预，利用贝叶斯模型平均得到最终预测及后验区间。 | E8: 灰色模型对小样本和缺失较宽容，BSTS能够处理趋势随时间变化及参数不确定性，适合本题“样本少、来源质量不一、冲击明显、必须给区间”的组合特征。 | F8: 将灰色系统的弱信息预测与贝叶斯状态空间融合，并按证据等级调整观测噪声；不是简单取均值，而是根据后验概率动态分配模型权重。 | G8: GM模型的近指数累积规律可能与疫情冲击冲突；BSTS结果受先验和变量选择影响，短样本下后验区间可能较宽；实现和解释成本高于ARIMAX＋ETS。
A9: 问题3 | B9: 方案1｜基础适配（主推荐） | C9: 动态弹性情景模型＋拉丁超立方Monte Carlo＋龙卷风敏感性 | D9: 以问题2基准预测为自然延续路径，把政策投入、核心客源和新业态指数的变化乘以相应弹性，形成乐观、基准和悲观路径；再在每个参数区间内进行拉丁超立方抽样，观察游客量和收入分布，并按输出变化幅度排序关键因素。 | E9: 题目明确要求三情景、敏感性和定量建议，但历史政策变量很稀疏。弹性模型参数少、透明，允许把规划目标和专家区间直接转为可审计假设，适合校赛论文时间限制。 | F9: 弹性不设为永久常数，而是加入政策生效时滞和逐年动态权重；联合抽样保留因素间相关性，相比单纯上下浮动10%的方法能给出概率分布和超标风险。 | G9: 弹性多由短历史或专家区间估计，因果解释有限；若政策、客源和新业态存在强交互，单一弹性会低估非线性；建议需同时报告参数区间而非只给一个点值。
A10: 问题3 | B10: 方案2｜创新融合（答辩亮点） | C10: 系统动力学（SD）＋贝叶斯网络风险传播＋多目标鲁棒优化 | D10: 系统动力学描述游客、接待能力、消费、财政再投入和新业态供给之间的反馈；贝叶斯网络计算宏观下行或公共事件向客流和收入传播的概率；多目标鲁棒优化在不同风险情景下选择兼顾收入增长、投入成本和波动风险的政策组合。 | E10: 问题3不仅要求预测，还要求把政策转成3—5条可操作建议。该组合可以表现“投入改善供给、供给吸引客流、收入反哺投入”的循环，也能把突发事件概率纳入政策方案比较。 | F10: 把因果反馈、概率风险和决策优化连成一体，使模型输出从情景曲线升级为政策组合；可使用分布鲁棒约束避免建议只在单一预测路径上有效。 | G10: 系统结构、条件概率和成本约束需要大量补充数据或专家赋值，主观性较强；若参数未经校准，复杂模型可能制造虚假的精确性，建议作为扩展模型并用基础方案交叉验证。

Sheet 模型流程
A1: 模型应用流程与决策节点
B3: 问题1：历史规律与基准增长模型
B5: 输入多版本长表 保留证据等级 | C5: → | D5: 口径是否一致？ 否：分序列/桥接 是：继续 | E5: → | F5: 缺失是否位于疫情期？ 是：累计约束补全 否：插值/比例桥接 | G5: → | H5: 变点是否显著？ 是：分段Gompertz 否：单段增长 | I5: → | J5: 输出趋势、冲击幅度 适用区间与误差
B8: 创新分支：若需同时表达来源质量和状态概率，则以质量加权贝叶斯局部趋势＋隐马尔可夫状态切换进行稳健性验证。
B12: 问题2：游客量与综合收入预测
B14: 输入清洗序列 对数/平稳性检查 | C14: → | D14: 样本是否少于30期？ 是：限制低阶模型 否：再考虑复杂模型 | E14: → | F14: 未来外生变量可得？ 是：ARIMAX 否：ETS/灰色模型 | G14: → | H14: 残差是否白噪声？ 否：调阶/变换 是：滚动验证 | I14: → | J14: 误差互补？ 是：动态加权组合 否：选最优单模
B17: 输出：2026—2030点预测、95%预测区间、MAE/RMSE/MAPE，以及与问题1基准模型的统一验证集比较。
B21: 问题3：情景、敏感性与量化建议
B23: 承接问题2 建立基准预测路径 | C23: → | D23: 驱动因素可量化？ 是：估计弹性 否：标准化指数 | E23: → | F23: 参数是否在历史/规划边界？ 否：重新标定 是：三情景赋值 | G23: → | H23: 非线性反馈显著？ 是：SD＋贝叶斯网络 否：动态弹性 | I23: → | J23: LHS Monte Carlo 敏感性排序 鲁棒建议
B26: 决策输出必须形成“因素—政策工具—投入强度—实施期—预期客流/收入增量—监测指标”的闭环。

Sheet 原始年度数据
A1: 官方优选年度宽表（原始层，不做覆盖）
A2: 来源：official_annual_summary_2010_2025.csv。空白保持为空；target、inferred、provisional等状态不得当作同等质量的官方实际值。
A3: 年份 | B3: 游客量(万人次) | C3: 游客状态 | D3: 直接收入(亿元) | E3: 直接收入状态 | F3: 综合收入(亿元) | G3: 综合收入状态 | H3: GDP(亿元) | I3: GDP状态 | J3: 第三产业(亿元) | K3: 第三产业状态 | L3: 来源ID | M3: 质量说明
A4: 2010 | B4: 848 | C4: observed_rounded | D4: 7.104247 | E4: inferred_from_yoy | F4: 35.521236 | G4: inferred_from_yoy | H4: 215.47 | I4: official_yearbook | J4: 136.23 | K4: official_yearbook | L4: gov_jz_report_2011;gov_jz_bulletin_2011;gov_tj_yearbook_2011_jixian | M4: 收入为同比反推；游客量为工作报告约数
A5: 2011 | B5: 1098.6 | C5: observed | D5: 9.2 | E5: observed | F5: 46 | G5: observed | H5: 250.11 | I5: official_yearbook | J5: 147.02 | K5: official_yearbook | L5: gov_jz_bulletin_2011;gov_tj_yearbook_2012_jixian | M5: 宏观指标采用后版年鉴回列值并保留公报初值于宏观长表
A6: 2012 | B6: 1152 | C6: observed_rounded | F6: 52 | G6: observed_rounded | H6: 333.3 | I6: provisional_estimate | L6: gov_jz_report_2013 | M6: 旅游为工作报告回顾值；GDP为预计值且待后续年鉴复核
A7: 2013 | B7: 1295 | C7: observed_cached | D7: 12.63 | E7: observed_cached | F7: 63.2 | G7: observed_cached | H7: 316.8 | I7: inferred_from_official_bulletin | J7: 187.5456 | K7: inferred_from_official_bulletin | L7: gov_jz_tourism_summary_2013;gov_jz_bulletin_2014 | M7: 旅游官方详情页当前下线；宏观值由2014公报回列信息推导
A8: 2014 | B8: 1553.4 | C8: observed_revised | D8: 15.8007 | E8: observed_revised | F8: 79 | G8: observed | H8: 361.1 | I8: official_initial | J8: 212.91 | K8: official_initial | L8: gov_jz_tourism_stats_2015;gov_jz_bulletin_2014 | M8: 游客和直接收入采用下一年统计表回列修订值
A9: 2015 | B9: 1818.72 | C9: observed_revised | D9: 18.7922 | E9: observed_revised | F9: 94 | G9: observed_supporting_attachment | H9: 409 | I9: provisional_estimate | L9: gov_jz_tourism_stats_2016;gov_jz_tourism_attachment_2015;gov_jz_report_2016 | M9: 综合收入证据层级较低；GDP为十二五回顾值
A10: 2016 | B10: 2086 | C10: observed_revised | D10: 21.9172 | E10: observed_revised | H10: 430 | I10: provisional_estimate | L10: gov_jz_tourism_stats_2017;gov_jz_report_2017 | M10: 未找到同口径综合收入；GDP为报告预计值
A11: 2017 | B11: 2392 | C11: observed | D11: 26.1347 | E11: observed | F11: 130 | G11: observed_rounded | L11: gov_jz_tourism_stats_2017;gov_jz_report_2018 | M11: 工作报告游客约数2400未覆盖统计表精确值2392
A12: 2018 | B12: 2660 | C12: observed_rounded | F12: 142 | G12: observed_rounded | H12: 380 | I12: provisional_estimate | L12: gov_jz_report_2019 | M12: GDP为工作报告预计值
A13: 2019 | B13: 2800 | C13: observed_rounded | F13: 165 | G13: observed_rounded | H13: 210.8 | I13: official_initial | J13: 129.92 | K13: official_initial | L13: gov_jz_report_2020;gov_jz_bulletin_2019 | M13: 宏观序列与2018年前口径存在明显断点
A14: 2020 | H14: 224.6 | I14: official_initial | J14: 142.55 | K14: official_initial | L14: gov_jz_bulletin_2020 | M14: 疫情年份未找到可核验的年度旅游总量
A15: 2021 | F15: 110 | G15: observed_rounded | H15: 274.2034 | I15: official_revised | J15: 161.9732 | K15: official_revised | L15: gov_jz_report_2022;gov_jz_yearbook_2022 | M15: 未找到精确游客量；宏观指标采用后版年鉴修订值
A16: 2022 | H16: 282.2414 | I16: official_revised | J16: 171.2106 | K16: official_revised | L16: gov_jz_yearbook_2023 | M16: 未找到可核验的年度游客量及实际综合收入
A17: 2023 | B17: 2363 | C17: observed_rounded | F17: 191.5 | G17: observed | H17: 288.3062 | I17: official_final | J17: 176.1714 | K17: official_final | L17: gov_jz_report_2024;gov_jz_yearbook_2024 | M17: 宏观指标采用2024年鉴最终核实值
A18: 2024 | B18: 2643 | C18: observed_rounded | F18: 221 | G18: observed_rounded | H18: 298.865 | I18: official_yearbook | J18: 183.9654 | K18: official_yearbook | L18: gov_jz_report_2025;gov_jz_yearbook_2024 | M18: 宏观指标采用2024年鉴现价值
A19: 2025 | H19: 311.94 | I19: official_initial | J19: 195.17 | K19: official_initial | L19: gov_jz_bulletin_2025 | M19: 政府报告仅给2025年目标和2021至2025累计值；不作为年度实际

Sheet 补充假设
A1: 缺失补全参数与约束（黄色单元格可编辑）
A2: 这些数值是建模假设或官方累计/目标约束，不是新增官方年度实际。修改黄色输入后，预处理结果、异常检测和趋势图会联动更新。
A3: 参数 | B3: 数值 | C3: 单位 | D3: 类型 | E3: 依据/计算逻辑 | F3: 可编辑 | G3: 建议敏感性范围
A4: 2021—2025游客累计 | B4: 10500 | C4: 万人次 | D4: 官方累计约束 | E4: 政府报告五年累计值，不拆作单年观测 | F4: 否 | G4: 固定
A5: 2021—2025综合收入累计 | B5: 792.5 | C5: 亿元 | D5: 官方累计约束 | E5: 政府报告五年累计值 | F5: 否 | G5: 固定
A6: 2025游客目标替代值 | B6: 2800 | C6: 万人次 | D6: 假设输入 | E6: 无年度实际值时暂以目标代替 | F6: 是 | G6: ±5%至±10%
A7: 2025综合收入目标替代值 | B7: 231 | C7: 亿元 | D7: 假设输入 | E7: 无年度实际值时暂以目标代替 | F7: 是 | G7: ±5%至±10%
A8: 2020游客保留率 | B8: 0.55 | C8: % | D8: 假设输入 | E8: 相对2019年，用于刻画首年疫情冲击 | F8: 是 | G8: 45%—65%
A9: 2020人均消费保留率 | B9: 0.9 | C9: % | D9: 假设输入 | E9: 相对2019人均旅游消费 | F9: 是 | G9: 80%—100%
A10: 综合收入/直接收入桥接倍数 | B10: 5 | C10: 倍 | D10: 假设输入 | E10: 2011、2013—2015、2017年关系约为5倍 | F10: 是 | G10: 4.8—5.2
A11: 2021综合收入观测 | B11: 110 | C11: 亿元 | D11: 官方观测 | E11: 用于分配2021—2022游客余量 | F11: 否 | G11: 固定
A12: 2023游客量观测 | B12: 2363 | C12: 万人次 | D12: 官方观测 | E12: 五年累计约束已知项 | F12: 否 | G12: 固定
A13: 2024游客量观测 | B13: 2643 | C13: 万人次 | D13: 官方观测 | E13: 五年累计约束已知项 | F13: 否 | G13: 固定
A14: 2023综合收入观测 | B14: 191.5 | C14: 亿元 | D14: 官方观测 | E14: 五年累计约束已知项 | F14: 否 | G14: 固定
A15: 2024综合收入观测 | B15: 221 | C15: 亿元 | D15: 官方观测 | E15: 五年累计约束已知项 | F15: 否 | G15: 固定
A16: 2021—2022游客余量 | B16: =B4-B6-B12-B13 -> 2694 | C16: 万人次 | D16: 公式输出 | E16: 五年累计－2023－2024－2025替代值 | F16: 否
A17: 2022综合收入 | B17: =B5-B7-B11-B14-B15 -> 39 | C17: 亿元 | D17: 公式输出 | E17: 五年累计－2021－2023－2024－2025替代值 | F17: 否
A18: 2021游客量 | B18: =B16*B11/(B11+B17) -> 1988.8591 | C18: 万人次 | D18: 公式输出 | E18: 游客余量按2021/2022收入占比分配 | F18: 否
A19: 2022游客量 | B19: =B16*B17/(B11+B17) -> 705.14094 | C19: 万人次 | D19: 公式输出 | E19: 游客余量按2021/2022收入占比分配 | F19: 否
A20: 2020游客量 | B20: =原始年度数据!B13*B8 -> 1540 | C20: 万人次 | D20: 公式输出 | E20: 2019游客量×2020保留率 | F20: 否
A21: 2020综合收入 | B21: =原始年度数据!F13/原始年度数据!B13*B20*B9 -> 81.675 | C21: 亿元 | D21: 公式输出 | E21: 2019人均消费×2020游客量×消费保留率 | F21: 否
A22: 2016综合收入 | B22: =原始年度数据!D10*B10 -> 109.586 | C22: 亿元 | D22: 公式输出 | E22: 2016直接收入×桥接倍数 | F22: 否
A23: 2017 GDP | B23: =AVERAGE(原始年度数据!H10,原始年度数据!H12) -> 405 | C23: 亿元 | D23: 公式输出 | E23: 2016与2018同口径段线性插值 | F23: 否

Sheet 预处理结果
A1: 建模主数据：原始值、补全值、异常标记与转换结果
A2: 规则：官方值优先；疫情期缺失采用累计约束＋明确假设；常规缺失采用比例桥接或同口径线性插值。IQR异常只标记不删除。Z-score用于回归/组合模型，LN用于稳定方差。
A3: 年份 | B3: 游客原始 | C3: 直接收入原始 | D3: 综合收入原始 | E3: GDP原始 | F3: 第三产业原始 | G3: 游客状态 | H3: 综合收入状态 | I3: GDP状态 | J3: 第三产业状态 | K3: 游客清洗值 | L3: 游客处理方法 | M3: 综合收入清洗值 | N3: 收入处理方法 | O3: GDP清洗值 | P3: GDP处理方法 | Q3: 第三产业清洗值 | R3: 第三产业处理方法 | S3: 游客同比 | T3: 收入同比 | U3: 游客IQR判定 | V3: 收入IQR判定 | W3: 疫情哑变量 | X3: GDP口径断点 | Y3: 游客Z | Z3: 收入Z | AA3: GDP Z | AB3: 第三产业Z | AC3: LN游客 | AD3: LN收入
A4: =原始年度数据!A4 -> 2010 | B4: =IF(原始年度数据!B4="","",原始年度数据!B4) -> 848 | C4: =IF(原始年度数据!D4="","",原始年度数据!D4) -> 7.104247 | D4: =IF(原始年度数据!F4="","",原始年度数据!F4) -> 35.521236 | E4: =IF(原始年度数据!H4="","",原始年度数据!H4) -> 215.47 | F4: =IF(原始年度数据!J4="","",原始年度数据!J4) -> 136.23 | G4: =IF(原始年度数据!C4="","",原始年度数据!C4) -> observed_rounded | H4: =IF(原始年度数据!G4="","",原始年度数据!G4) -> inferred_from_yoy | I4: =IF(原始年度数据!I4="","",原始年度数据!I4) -> official_yearbook | J4: =IF(原始年度数据!K4="","",原始年度数据!K4) -> official_yearbook | K4: =B4 -> 848 | L4: 保留官方优选值 | M4: =D4 -> 35.521236 | N4: 保留官方优选值 | O4: =E4 -> 215.47 | P4: 保留官方优选值 | Q4: =F4 -> 136.23 | R4: 保留官方优选值 | W4: =IF(AND(A4>=2020,A4<=2022),1,0) -> 0 | X4: =IF(A4>=2019,1,0) -> 0 | Y4: =(K4-AVERAGE($K$4:$K$19))/_xludf.STDEV.S($K$4:$K$19) -> #NAME? | Z4: =(M4-AVERAGE($M$4:$M$19))/_xludf.STDEV.S($M$4:$M$19) -> #NAME? | AA4: =(O4-AVERAGE($O$4:$O$19))/_xludf.STDEV.S($O$4:$O$19) -> #NAME? | AB4: =(Q4-AVERAGE($Q$4:$Q$19))/_xludf.STDEV.S($Q$4:$Q$19) -> #NAME? | AC4: =LN(K4) -> 6.7428806 | AD4: =LN(M4) -> 3.5701307
A5: =原始年度数据!A5 -> 2011 | B5: =IF(原始年度数据!B5="","",原始年度数据!B5) -> 1098.6 | C5: =IF(原始年度数据!D5="","",原始年度数据!D5) -> 9.2 | D5: =IF(原始年度数据!F5="","",原始年度数据!F5) -> 46 | E5: =IF(原始年度数据!H5="","",原始年度数据!H5) -> 250.11 | F5: =IF(原始年度数据!J5="","",原始年度数据!J5) -> 147.02 | G5: =IF(原始年度数据!C5="","",原始年度数据!C5) -> observed | H5: =IF(原始年度数据!G5="","",原始年度数据!G5) -> observed | I5: =IF(原始年度数据!I5="","",原始年度数据!I5) -> official_yearbook | J5: =IF(原始年度数据!K5="","",原始年度数据!K5) -> official_yearbook | K5: =B5 -> 1098.6 | L5: 保留官方优选值 | M5: =D5 -> 46 | N5: 保留官方优选值 | O5: =E5 -> 250.11 | P5: 保留官方优选值 | Q5: =F5 -> 147.02 | R5: 保留官方优选值 | S5: =K5/K4-1 -> 0.29551887 | T5: =M5/M4-1 -> 0.29499998 | U5: =IF(OR(S5<异常检测!$B$7,S5>异常检测!$B$8),"保留-结构冲击","正常") -> 正常 | V5: =IF(OR(T5<异常检测!$E$7,T5>异常检测!$E$8),"保留-结构冲击","正常") -> 正常 | W5: =IF(AND(A5>=2020,A5<=2022),1,0) -> 0 | X5: =IF(A5>=2019,1,0) -> 0 | Y5: =(K5-AVERAGE($K$4:$K$19))/_xludf.STDEV.S($K$4:$K$19) -> #NAME? | Z5: =(M5-AVERAGE($M$4:$M$19))/_xludf.STDEV.S($M$4:$M$19) -> #NAME? | AA5: =(O5-AVERAGE($O$4:$O$19))/_xludf.STDEV.S($O$4:$O$19) -> #NAME? | AB5: =(Q5-AVERAGE($Q$4:$Q$19))/_xludf.STDEV.S($Q$4:$Q$19) -> #NAME? | AC5: =LN(K5) -> 7.0017919 | AD5: =LN(M5) -> 3.8286414
A6: =原始年度数据!A6 -> 2012 | B6: =IF(原始年度数据!B6="","",原始年度数据!B6) -> 1152 | C6: =IF(原始年度数据!D6="","",原始年度数据!D6) | D6: =IF(原始年度数据!F6="","",原始年度数据!F6) -> 52 | E6: =IF(原始年度数据!H6="","",原始年度数据!H6) -> 333.3 | F6: =IF(原始年度数据!J6="","",原始年度数据!J6) | G6: =IF(原始年度数据!C6="","",原始年度数据!C6) -> observed_rounded | H6: =IF(原始年度数据!G6="","",原始年度数据!G6) -> observed_rounded | I6: =IF(原始年度数据!I6="","",原始年度数据!I6) -> provisional_estimate | J6: =IF(原始年度数据!K6="","",原始年度数据!K6) | K6: =B6 -> 1152 | L6: 保留官方优选值 | M6: =D6 -> 52 | N6: 保留官方优选值 | O6: =E6 -> 333.3 | P6: 保留官方优选值 | Q6: =O6*((Q5/O5)+((A6-A5)/(A7-A5))*((Q7/O7)-(Q5/O5))) -> 196.61723 | R6: 第三产业/GDP占比线性插值 | S6: =K6/K5-1 -> 0.048607318 | T6: =M6/M5-1 -> 0.13043478 | U6: =IF(OR(S6<异常检测!$B$7,S6>异常检测!$B$8),"保留-结构冲击","正常") -> 正常 | V6: =IF(OR(T6<异常检测!$E$7,T6>异常检测!$E$8),"保留-结构冲击","正常") -> 正常 | W6: =IF(AND(A6>=2020,A6<=2022),1,0) -> 0 | X6: =IF(A6>=2019,1,0) -> 0 | Y6: =(K6-AVERAGE($K$4:$K$19))/_xludf.STDEV.S($K$4:$K$19) -> #NAME? | Z6: =(M6-AVERAGE($M$4:$M$19))/_xludf.STDEV.S($M$4:$M$19) -> #NAME? | AA6: =(O6-AVERAGE($O$4:$O$19))/_xludf.STDEV.S($O$4:$O$19) -> #NAME? | AB6: =(Q6-AVERAGE($Q$4:$Q$19))/_xludf.STDEV.S($Q$4:$Q$19) -> #NAME? | AC6: =LN(K6) -> 7.0492548 | AD6: =LN(M6) -> 3.9512437
A7: =原始年度数据!A7 -> 2013 | B7: =IF(原始年度数据!B7="","",原始年度数据!B7) -> 1295 | C7: =IF(原始年度数据!D7="","",原始年度数据!D7) -> 12.63 | D7: =IF(原始年度数据!F7="","",原始年度数据!F7) -> 63.2 | E7: =IF(原始年度数据!H7="","",原始年度数据!H7) -> 316.8 | F7: =IF(原始年度数据!J7="","",原始年度数据!J7) -> 187.5456 | G7: =IF(原始年度数据!C7="","",原始年度数据!C7) -> observed_cached | H7: =IF(原始年度数据!G7="","",原始年度数据!G7) -> observed_cached | I7: =IF(原始年度数据!I7="","",原始年度数据!I7) -> inferred_from_official_bulletin | J7: =IF(原始年度数据!K7="","",原始年度数据!K7) -> inferred_from_official_bulletin | K7: =B7 -> 1295 | L7: 保留官方优选值 | M7: =D7 -> 63.2 | N7: 保留官方优选值 | O7: =E7 -> 316.8 | P7: 保留官方优选值 | Q7: =F7 -> 187.5456 | R7: 保留官方优选值 | S7: =K7/K6-1 -> 0.12413194 | T7: =M7/M6-1 -> 0.21538462 | U7: =IF(OR(S7<异常检测!$B$7,S7>异常检测!$B$8),"保留-结构冲击","正常") -> 正常 | V7: =IF(OR(T7<异常检测!$E$7,T7>异常检测!$E$8),"保留-结构冲击","正常") -> 正常 | W7: =IF(AND(A7>=2020,A7<=2022),1,0) -> 0 | X7: =IF(A7>=2019,1,0) -> 0 | Y7: =(K7-AVERAGE($K$4:$K$19))/_xludf.STDEV.S($K$4:$K$19) -> #NAME? | Z7: =(M7-AVERAGE($M$4:$M$19))/_xludf.STDEV.S($M$4:$M$19) -> #NAME? | AA7: =(O7-AVERAGE($O$4:$O$19))/_xludf.STDEV.S($O$4:$O$19) -> #NAME? | AB7: =(Q7-AVERAGE($Q$4:$Q$19))/_xludf.STDEV.S($Q$4:$Q$19) -> #NAME? | AC7: =LN(K7) -> 7.166266 | AD7: =LN(M7) -> 4.1463043
A8: =原始年度数据!A8 -> 2014 | B8: =IF(原始年度数据!B8="","",原始年度数据!B8) -> 1553.4 | C8: =IF(原始年度数据!D8="","",原始年度数据!D8) -> 15.8007 | D8: =IF(原始年度数据!F8="","",原始年度数据!F8) -> 79 | E8: =IF(原始年度数据!H8="","",原始年度数据!H8) -> 361.1 | F8: =IF(原始年度数据!J8="","",原始年度数据!J8) -> 212.91 | G8: =IF(原始年度数据!C8="","",原始年度数据!C8) -> observed_revised | H8: =IF(原始年度数据!G8="","",原始年度数据!G8) -> observed | I8: =IF(原始年度数据!I8="","",原始年度数据!I8) -> official_initial | J8: =IF(原始年度数据!K8="","",原始年度数据!K8) -> official_initial | K8: =B8 -> 1553.4 | L8: 保留官方优选值 | M8: =D8 -> 79 | N8: 保留官方优选值 | O8: =E8 -> 361.1 | P8: 保留官方优选值 | Q8: =F8 -> 212.91 | R8: 保留官方优选值 | S8: =K8/K7-1 -> 0.19953668 | T8: =M8/M7-1 -> 0.25 | U8: =IF(OR(S8<异常检测!$B$7,S8>异常检测!$B$8),"保留-结构冲击","正常") -> 正常 | V8: =IF(OR(T8<异常检测!$E$7,T8>异常检测!$E$8),"保留-结构冲击","正常") -> 正常 | W8: =IF(AND(A8>=2020,A8<=2022),1,0) -> 0 | X8: =IF(A8>=2019,1,0) -> 0 | Y8: =(K8-AVERAGE($K$4:$K$19))/_xludf.STDEV.S($K$4:$K$19) -> #NAME? | Z8: =(M8-AVERAGE($M$4:$M$19))/_xludf.STDEV.S($M$4:$M$19) -> #NAME? | AA8: =(O8-AVERAGE($O$4:$O$19))/_xludf.STDEV.S($O$4:$O$19) -> #NAME? | AB8: =(Q8-AVERAGE($Q$4:$Q$19))/_xludf.STDEV.S($Q$4:$Q$19) -> #NAME? | AC8: =LN(K8) -> 7.3482014 | AD8: =LN(M8) -> 4.3694479
A9: =原始年度数据!A9 -> 2015 | B9: =IF(原始年度数据!B9="","",原始年度数据!B9) -> 1818.72 | C9: =IF(原始年度数据!D9="","",原始年度数据!D9) -> 18.7922 | D9: =IF(原始年度数据!F9="","",原始年度数据!F9) -> 94 | E9: =IF(原始年度数据!H9="","",原始年度数据!H9) -> 409 | F9: =IF(原始年度数据!J9="","",原始年度数据!J9) | G9: =IF(原始年度数据!C9="","",原始年度数据!C9) -> observed_revised | H9: =IF(原始年度数据!G9="","",原始年度数据!G9) -> observed_supporting_attachment | I9: =IF(原始年度数据!I9="","",原始年度数据!I9) -> provisional_estimate | J9: =IF(原始年度数据!K9="","",原始年度数据!K9) | K9: =B9 -> 1818.72 | L9: 保留官方优选值 | M9: =D9 -> 94 | N9: 保留官方优选值 | O9: =E9 -> 409 | P9: 保留官方优选值 | Q9: =O9*((Q8/O8)+((A9-A8)/(A13-A8))*((Q13/O13)-(Q8/O8))) -> 243.33693 | R9: 2014—2019占比桥接 | S9: =K9/K8-1 -> 0.17079954 | T9: =M9/M8-1 -> 0.18987342 | U9: =IF(OR(S9<异常检测!$B$7,S9>异常检测!$B$8),"保留-结构冲击","正常") -> 正常 | V9: =IF(OR(T9<异常检测!$E$7,T9>异常检测!$E$8),"保留-结构冲击","正常") -> 正常 | W9: =IF(AND(A9>=2020,A9<=2022),1,0) -> 0 | X9: =IF(A9>=2019,1,0) -> 0 | Y9: =(K9-AVERAGE($K$4:$K$19))/_xludf.STDEV.S($K$4:$K$19) -> #NAME? | Z9: =(M9-AVERAGE($M$4:$M$19))/_xludf.STDEV.S($M$4:$M$19) -> #NAME? | AA9: =(O9-AVERAGE($O$4:$O$19))/_xludf.STDEV.S($O$4:$O$19) -> #NAME? | AB9: =(Q9-AVERAGE($Q$4:$Q$19))/_xludf.STDEV.S($Q$4:$Q$19) -> #NAME? | AC9: =LN(K9) -> 7.5058882 | AD9: =LN(M9) -> 4.5432948
A10: =原始年度数据!A10 -> 2016 | B10: =IF(原始年度数据!B10="","",原始年度数据!B10) -> 2086 | C10: =IF(原始年度数据!D10="","",原始年度数据!D10) -> 21.9172 | D10: =IF(原始年度数据!F10="","",原始年度数据!F10) | E10: =IF(原始年度数据!H10="","",原始年度数据!H10) -> 430 | F10: =IF(原始年度数据!J10="","",原始年度数据!J10) | G10: =IF(原始年度数据!C10="","",原始年度数据!C10) -> observed_revised | H10: =IF(原始年度数据!G10="","",原始年度数据!G10) | I10: =IF(原始年度数据!I10="","",原始年度数据!I10) -> provisional_estimate | J10: =IF(原始年度数据!K10="","",原始年度数据!K10) | K10: =B10 -> 2086 | L10: 保留官方优选值 | M10: =补充假设!$B$22 -> 109.586 | N10: 直接收入×历史桥接倍数 | O10: =E10 -> 430 | P10: 保留官方优选值 | Q10: =O10*((Q8/O8)+((A10-A8)/(A13-A8))*((Q13/O13)-(Q8/O8))) -> 258.12752 | R10: 2014—2019占比桥接 | S10: =K10/K9-1 -> 0.1469605 | T10: =M10/M9-1 -> 0.16580851 | U10: =IF(OR(S10<异常检测!$B$7,S10>异常检测!$B$8),"保留-结构冲击","正常") -> 正常 | V10: =IF(OR(T10<异常检测!$E$7,T10>异常检测!$E$8),"保留-结构冲击","正常") -> 正常 | W10: =IF(AND(A10>=2020,A10<=2022),1,0) -> 0 | X10: =IF(A10>=2019,1,0) -> 0 | Y10: =(K10-AVERAGE($K$4:$K$19))/_xludf.STDEV.S($K$4:$K$19) -> #NAME? | Z10: =(M10-AVERAGE($M$4:$M$19))/_xludf.STDEV.S($M$4:$M$19) -> #NAME? | AA10: =(O10-AVERAGE($O$4:$O$19))/_xludf.STDEV.S($O$4:$O$19) -> #NAME? | AB10: =(Q10-AVERAGE($Q$4:$Q$19))/_xludf.STDEV.S($Q$4:$Q$19) -> #NAME? | AC10: =LN(K10) -> 7.6430036 | AD10: =LN(M10) -> 4.6967096
A11: =原始年度数据!A11 -> 2017 | B11: =IF(原始年度数据!B11="","",原始年度数据!B11) -> 2392 | C11: =IF(原始年度数据!D11="","",原始年度数据!D11) -> 26.1347 | D11: =IF(原始年度数据!F11="","",原始年度数据!F11) -> 130 | E11: =IF(原始年度数据!H11="","",原始年度数据!H11) | F11: =IF(原始年度数据!J11="","",原始年度数据!J11) | G11: =IF(原始年度数据!C11="","",原始年度数据!C11) -> observed | H11: =IF(原始年度数据!G11="","",原始年度数据!G11) -> observed_rounded | I11: =IF(原始年度数据!I11="","",原始年度数据!I11) | J11: =IF(原始年度数据!K11="","",原始年度数据!K11) | K11: =B11 -> 2392 | L11: 保留官方优选值 | M11: =D11 -> 130 | N11: 保留官方优选值 | O11: =补充假设!$B$23 -> 405 | P11: 同口径段线性插值 | Q11: =O11*((Q8/O8)+((A11-A8)/(A13-A8))*((Q13/O13)-(Q8/O8))) -> 245.28311 | R11: 2014—2019占比桥接 | S11: =K11/K10-1 -> 0.14669223 | T11: =M11/M10-1 -> 0.18628292 | U11: =IF(OR(S11<异常检测!$B$7,S11>异常检测!$B$8),"保留-结构冲击","正常") -> 正常 | V11: =IF(OR(T11<异常检测!$E$7,T11>异常检测!$E$8),"保留-结构冲击","正常") -> 正常 | W11: =IF(AND(A11>=2020,A11<=2022),1,0) -> 0 | X11: =IF(A11>=2019,1,0) -> 0 | Y11: =(K11-AVERAGE($K$4:$K$19))/_xludf.STDEV.S($K$4:$K$19) -> #NAME? | Z11: =(M11-AVERAGE($M$4:$M$19))/_xludf.STDEV.S($M$4:$M$19) -> #NAME? | AA11: =(O11-AVERAGE($O$4:$O$19))/_xludf.STDEV.S($O$4:$O$19) -> #NAME? | AB11: =(Q11-AVERAGE($Q$4:$Q$19))/_xludf.STDEV.S($Q$4:$Q$19) -> #NAME? | AC11: =LN(K11) -> 7.7798851 | AD11: =LN(M11) -> 4.8675345
A12: =原始年度数据!A12 -> 2018 | B12: =IF(原始年度数据!B12="","",原始年度数据!B12) -> 2660 | C12: =IF(原始年度数据!D12="","",原始年度数据!D12) | D12: =IF(原始年度数据!F12="","",原始年度数据!F12) -> 142 | E12: =IF(原始年度数据!H12="","",原始年度数据!H12) -> 380 | F12: =IF(原始年度数据!J12="","",原始年度数据!J12) | G12: =IF(原始年度数据!C12="","",原始年度数据!C12) -> observed_rounded | H12: =IF(原始年度数据!G12="","",原始年度数据!G12) -> observed_rounded | I12: =IF(原始年度数据!I12="","",原始年度数据!I12) -> provisional_estimate | J12: =IF(原始年度数据!K12="","",原始年度数据!K12) | K12: =B12 -> 2660 | L12: 保留官方优选值 | M12: =D12 -> 142 | N12: 保留官方优选值 | O12: =E12 -> 380 | P12: 保留官方优选值 | Q12: =O12*((Q8/O8)+((A12-A8)/(A13-A8))*((Q13/O13)-(Q8/O8))) -> 232.17166 | R12: 2014—2019占比桥接 | S12: =K12/K11-1 -> 0.11204013 | T12: =M12/M11-1 -> 0.092307692 | U12: =IF(OR(S12<异常检测!$B$7,S12>异常检测!$B$8),"保留-结构冲击","正常") -> 正常 | V12: =IF(OR(T12<异常检测!$E$7,T12>异常检测!$E$8),"保留-结构冲击","正常") -> 正常 | W12: =IF(AND(A12>=2020,A12<=2022),1,0) -> 0 | X12: =IF(A12>=2019,1,0) -> 0 | Y12: =(K12-AVERAGE($K$4:$K$19))/_xludf.STDEV.S($K$4:$K$19) -> #NAME? | Z12: =(M12-AVERAGE($M$4:$M$19))/_xludf.STDEV.S($M$4:$M$19) -> #NAME? | AA12: =(O12-AVERAGE($O$4:$O$19))/_xludf.STDEV.S($O$4:$O$19) -> #NAME? | AB12: =(Q12-AVERAGE($Q$4:$Q$19))/_xludf.STDEV.S($Q$4:$Q$19) -> #NAME? | AC12: =LN(K12) -> 7.8860814 | AD12: =LN(M12) -> 4.9558271
A13: =原始年度数据!A13 -> 2019 | B13: =IF(原始年度数据!B13="","",原始年度数据!B13) -> 2800 | C13: =IF(原始年度数据!D13="","",原始年度数据!D13) | D13: =IF(原始年度数据!F13="","",原始年度数据!F13) -> 165 | E13: =IF(原始年度数据!H13="","",原始年度数据!H13) -> 210.8 | F13: =IF(原始年度数据!J13="","",原始年度数据!J13) -> 129.92 | G13: =IF(原始年度数据!C13="","",原始年度数据!C13) -> observed_rounded | H13: =IF(原始年度数据!G13="","",原始年度数据!G13) -> observed_rounded | I13: =IF(原始年度数据!I13="","",原始年度数据!I13) -> official_initial | J13: =IF(原始年度数据!K13="","",原始年度数据!K13) -> official_initial | K13: =B13 -> 2800 | L13: 保留官方优选值 | M13: =D13 -> 165 | N13: 保留官方优选值 | O13: =E13 -> 210.8 | P13: 保留官方优选值 | Q13: =F13 -> 129.92 | R13: 保留官方优选值 | S13: =K13/K12-1 -> 0.052631579 | T13: =M13/M12-1 -> 0.16197183 | U13: =IF(OR(S13<异常检测!$B$7,S13>异常检测!$B$8),"保留-结构冲击","正常") -> 正常 | V13: =IF(OR(T13<异常检测!$E$7,T13>异常检测!$E$8),"保留-结构冲击","正常") -> 正常 | W13: =IF(AND(A13>=2020,A13<=2022),1,0) -> 0 | X13: =IF(A13>=2019,1,0) -> 1 | Y13: =(K13-AVERAGE($K$4:$K$19))/_xludf.STDEV.S($K$4:$K$19) -> #NAME? | Z13: =(M13-AVERAGE($M$4:$M$19))/_xludf.STDEV.S($M$4:$M$19) -> #NAME? | AA13: =(O13-AVERAGE($O$4:$O$19))/_xludf.STDEV.S($O$4:$O$19) -> #NAME? | AB13: =(Q13-AVERAGE($Q$4:$Q$19))/_xludf.STDEV.S($Q$4:$Q$19) -> #NAME? | AC13: =LN(K13) -> 7.9373747 | AD13: =LN(M13) -> 5.1059455
A14: =原始年度数据!A14 -> 2020 | B14: =IF(原始年度数据!B14="","",原始年度数据!B14) | C14: =IF(原始年度数据!D14="","",原始年度数据!D14) | D14: =IF(原始年度数据!F14="","",原始年度数据!F14) | E14: =IF(原始年度数据!H14="","",原始年度数据!H14) -> 224.6 | F14: =IF(原始年度数据!J14="","",原始年度数据!J14) -> 142.55 | G14: =IF(原始年度数据!C14="","",原始年度数据!C14) | H14: =IF(原始年度数据!G14="","",原始年度数据!G14) | I14: =IF(原始年度数据!I14="","",原始年度数据!I14) -> official_initial | J14: =IF(原始年度数据!K14="","",原始年度数据!K14) -> official_initial | K14: =补充假设!$B$20 -> 1540 | L14: 2019×疫情保留率（假设） | M14: =补充假设!$B$21 -> 81.675 | N14: 2019人均消费×游客量×保留率 | O14: =E14 -> 224.6 | P14: 保留官方优选值 | Q14: =F14 -> 142.55 | R14: 保留官方优选值 | S14: =K14/K13-1 -> -0.45 | T14: =M14/M13-1 -> -0.505 | U14: =IF(OR(S14<异常检测!$B$7,S14>异常检测!$B$8),"保留-结构冲击","正常") -> 保留-结构冲击 | V14: =IF(OR(T14<异常检测!$E$7,T14>异常检测!$E$8),"保留-结构冲击","正常") -> 保留-结构冲击 | W14: =IF(AND(A14>=2020,A14<=2022),1,0) -> 1 | X14: =IF(A14>=2019,1,0) -> 1 | Y14: =(K14-AVERAGE($K$4:$K$19))/_xludf.STDEV.S($K$4:$K$19) -> #NAME? | Z14: =(M14-AVERAGE($M$4:$M$19))/_xludf.STDEV.S($M$4:$M$19) -> #NAME? | AA14: =(O14-AVERAGE($O$4:$O$19))/_xludf.STDEV.S($O$4:$O$19) -> #NAME? | AB14: =(Q14-AVERAGE($Q$4:$Q$19))/_xludf.STDEV.S($Q$4:$Q$19) -> #NAME? | AC14: =LN(K14) -> 7.3395377 | AD14: =LN(M14) -> 4.402748
A15: =原始年度数据!A15 -> 2021 | B15: =IF(原始年度数据!B15="","",原始年度数据!B15) | C15: =IF(原始年度数据!D15="","",原始年度数据!D15) | D15: =IF(原始年度数据!F15="","",原始年度数据!F15) -> 110 | E15: =IF(原始年度数据!H15="","",原始年度数据!H15) -> 274.2034 | F15: =IF(原始年度数据!J15="","",原始年度数据!J15) -> 161.9732 | G15: =IF(原始年度数据!C15="","",原始年度数据!C15) | H15: =IF(原始年度数据!G15="","",原始年度数据!G15) -> observed_rounded | I15: =IF(原始年度数据!I15="","",原始年度数据!I15) -> official_revised | J15: =IF(原始年度数据!K15="","",原始年度数据!K15) -> official_revised | K15: =补充假设!$B$18 -> 1988.8591 | L15: 累计余量按收入份额分配 | M15: =D15 -> 110 | N15: 保留官方优选值 | O15: =E15 -> 274.2034 | P15: 保留官方优选值 | Q15: =F15 -> 161.9732 | R15: 保留官方优选值 | S15: =K15/K14-1 -> 0.29146692 | T15: =M15/M14-1 -> 0.34680135 | U15: =IF(OR(S15<异常检测!$B$7,S15>异常检测!$B$8),"保留-结构冲击","正常") -> 正常 | V15: =IF(OR(T15<异常检测!$E$7,T15>异常检测!$E$8),"保留-结构冲击","正常") -> 正常 | W15: =IF(AND(A15>=2020,A15<=2022),1,0) -> 1 | X15: =IF(A15>=2019,1,0) -> 1 | Y15: =(K15-AVERAGE($K$4:$K$19))/_xludf.STDEV.S($K$4:$K$19) -> #NAME? | Z15: =(M15-AVERAGE($M$4:$M$19))/_xludf.STDEV.S($M$4:$M$19) -> #NAME? | AA15: =(O15-AVERAGE($O$4:$O$19))/_xludf.STDEV.S($O$4:$O$19) -> #NAME? | AB15: =(Q15-AVERAGE($Q$4:$Q$19))/_xludf.STDEV.S($Q$4:$Q$19) -> #NAME? | AC15: =LN(K15) -> 7.5953164 | AD15: =LN(M15) -> 4.7004804
A16: =原始年度数据!A16 -> 2022 | B16: =IF(原始年度数据!B16="","",原始年度数据!B16) | C16: =IF(原始年度数据!D16="","",原始年度数据!D16) | D16: =IF(原始年度数据!F16="","",原始年度数据!F16) | E16: =IF(原始年度数据!H16="","",原始年度数据!H16) -> 282.2414 | F16: =IF(原始年度数据!J16="","",原始年度数据!J16) -> 171.2106 | G16: =IF(原始年度数据!C16="","",原始年度数据!C16) | H16: =IF(原始年度数据!G16="","",原始年度数据!G16) | I16: =IF(原始年度数据!I16="","",原始年度数据!I16) -> official_revised | J16: =IF(原始年度数据!K16="","",原始年度数据!K16) -> official_revised | K16: =补充假设!$B$19 -> 705.14094 | L16: 累计余量按收入份额分配 | M16: =补充假设!$B$17 -> 39 | N16: 五年累计约束反推 | O16: =E16 -> 282.2414 | P16: 保留官方优选值 | Q16: =F16 -> 171.2106 | R16: 保留官方优选值 | S16: =K16/K15-1 -> -0.64545455 | T16: =M16/M15-1 -> -0.64545455 | U16: =IF(OR(S16<异常检测!$B$7,S16>异常检测!$B$8),"保留-结构冲击","正常") -> 保留-结构冲击 | V16: =IF(OR(T16<异常检测!$E$7,T16>异常检测!$E$8),"保留-结构冲击","正常") -> 保留-结构冲击 | W16: =IF(AND(A16>=2020,A16<=2022),1,0) -> 1 | X16: =IF(A16>=2019,1,0) -> 1 | Y16: =(K16-AVERAGE($K$4:$K$19))/_xludf.STDEV.S($K$4:$K$19) -> #NAME? | Z16: =(M16-AVERAGE($M$4:$M$19))/_xludf.STDEV.S($M$4:$M$19) -> #NAME? | AA16: =(O16-AVERAGE($O$4:$O$19))/_xludf.STDEV.S($O$4:$O$19) -> #NAME? | AB16: =(Q16-AVERAGE($Q$4:$Q$19))/_xludf.STDEV.S($Q$4:$Q$19) -> #NAME? | AC16: =LN(K16) -> 6.5583977 | AD16: =LN(M16) -> 3.6635616
A17: =原始年度数据!A17 -> 2023 | B17: =IF(原始年度数据!B17="","",原始年度数据!B17) -> 2363 | C17: =IF(原始年度数据!D17="","",原始年度数据!D17) | D17: =IF(原始年度数据!F17="","",原始年度数据!F17) -> 191.5 | E17: =IF(原始年度数据!H17="","",原始年度数据!H17) -> 288.3062 | F17: =IF(原始年度数据!J17="","",原始年度数据!J17) -> 176.1714 | G17: =IF(原始年度数据!C17="","",原始年度数据!C17) -> observed_rounded | H17: =IF(原始年度数据!G17="","",原始年度数据!G17) -> observed | I17: =IF(原始年度数据!I17="","",原始年度数据!I17) -> official_final | J17: =IF(原始年度数据!K17="","",原始年度数据!K17) -> official_final | K17: =B17 -> 2363 | L17: 保留官方优选值 | M17: =D17 -> 191.5 | N17: 保留官方优选值 | O17: =E17 -> 288.3062 | P17: 保留官方优选值 | Q17: =F17 -> 176.1714 | R17: 保留官方优选值 | S17: =K17/K16-1 -> 2.3511031 | T17: =M17/M16-1 -> 3.9102564 | U17: =IF(OR(S17<异常检测!$B$7,S17>异常检测!$B$8),"保留-结构冲击","正常") -> 保留-结构冲击 | V17: =IF(OR(T17<异常检测!$E$7,T17>异常检测!$E$8),"保留-结构冲击","正常") -> 保留-结构冲击 | W17: =IF(AND(A17>=2020,A17<=2022),1,0) -> 0 | X17: =IF(A17>=2019,1,0) -> 1 | Y17: =(K17-AVERAGE($K$4:$K$19))/_xludf.STDEV.S($K$4:$K$19) -> #NAME? | Z17: =(M17-AVERAGE($M$4:$M$19))/_xludf.STDEV.S($M$4:$M$19) -> #NAME? | AA17: =(O17-AVERAGE($O$4:$O$19))/_xludf.STDEV.S($O$4:$O$19) -> #NAME? | AB17: =(Q17-AVERAGE($Q$4:$Q$19))/_xludf.STDEV.S($Q$4:$Q$19) -> #NAME? | AC17: =LN(K17) -> 7.7676873 | AD17: =LN(M17) -> 5.2548878
A18: =原始年度数据!A18 -> 2024 | B18: =IF(原始年度数据!B18="","",原始年度数据!B18) -> 2643 | C18: =IF(原始年度数据!D18="","",原始年度数据!D18) | D18: =IF(原始年度数据!F18="","",原始年度数据!F18) -> 221 | E18: =IF(原始年度数据!H18="","",原始年度数据!H18) -> 298.865 | F18: =IF(原始年度数据!J18="","",原始年度数据!J18) -> 183.9654 | G18: =IF(原始年度数据!C18="","",原始年度数据!C18) -> observed_rounded | H18: =IF(原始年度数据!G18="","",原始年度数据!G18) -> observed_rounded | I18: =IF(原始年度数据!I18="","",原始年度数据!I18) -> official_yearbook | J18: =IF(原始年度数据!K18="","",原始年度数据!K18) -> official_yearbook | K18: =B18 -> 2643 | L18: 保留官方优选值 | M18: =D18 -> 221 | N18: 保留官方优选值 | O18: =E18 -> 298.865 | P18: 保留官方优选值 | Q18: =F18 -> 183.9654 | R18: 保留官方优选值 | S18: =K18/K17-1 -> 0.11849344 | T18: =M18/M17-1 -> 0.154047 | U18: =IF(OR(S18<异常检测!$B$7,S18>异常检测!$B$8),"保留-结构冲击","正常") -> 正常 | V18: =IF(OR(T18<异常检测!$E$7,T18>异常检测!$E$8),"保留-结构冲击","正常") -> 正常 | W18: =IF(AND(A18>=2020,A18<=2022),1,0) -> 0 | X18: =IF(A18>=2019,1,0) -> 1 | Y18: =(K18-AVERAGE($K$4:$K$19))/_xludf.STDEV.S($K$4:$K$19) -> #NAME? | Z18: =(M18-AVERAGE($M$4:$M$19))/_xludf.STDEV.S($M$4:$M$19) -> #NAME? | AA18: =(O18-AVERAGE($O$4:$O$19))/_xludf.STDEV.S($O$4:$O$19) -> #NAME? | AB18: =(Q18-AVERAGE($Q$4:$Q$19))/_xludf.STDEV.S($Q$4:$Q$19) -> #NAME? | AC18: =LN(K18) -> 7.8796699 | AD18: =LN(M18) -> 5.3981627
A19: =原始年度数据!A19 -> 2025 | B19: =IF(原始年度数据!B19="","",原始年度数据!B19) | C19: =IF(原始年度数据!D19="","",原始年度数据!D19) | D19: =IF(原始年度数据!F19="","",原始年度数据!F19) | E19: =IF(原始年度数据!H19="","",原始年度数据!H19) -> 311.94 | F19: =IF(原始年度数据!J19="","",原始年度数据!J19) -> 195.17 | G19: =IF(原始年度数据!C19="","",原始年度数据!C19) | H19: =IF(原始年度数据!G19="","",原始年度数据!G19) | I19: =IF(原始年度数据!I19="","",原始年度数据!I19) -> official_initial | J19: =IF(原始年度数据!K19="","",原始年度数据!K19) -> official_initial | K19: =补充假设!$B$6 -> 2800 | L19: 目标值替代，非年度实际 | M19: =补充假设!$B$7 -> 231 | N19: 目标值替代，非年度实际 | O19: =E19 -> 311.94 | P19: 保留官方优选值 | Q19: =F19 -> 195.17 | R19: 保留官方优选值 | S19: =K19/K18-1 -> 0.059402194 | T19: =M19/M18-1 -> 0.045248869 | U19: =IF(OR(S19<异常检测!$B$7,S19>异常检测!$B$8),"保留-结构冲击","正常") -> 正常 | V19: =IF(OR(T19<异常检测!$E$7,T19>异常检测!$E$8),"保留-结构冲击","正常") -> 正常 | W19: =IF(AND(A19>=2020,A19<=2022),1,0) -> 0 | X19: =IF(A19>=2019,1,0) -> 1 | Y19: =(K19-AVERAGE($K$4:$K$19))/_xludf.STDEV.S($K$4:$K$19) -> #NAME? | Z19: =(M19-AVERAGE($M$4:$M$19))/_xludf.STDEV.S($M$4:$M$19) -> #NAME? | AA19: =(O19-AVERAGE($O$4:$O$19))/_xludf.STDEV.S($O$4:$O$19) -> #NAME? | AB19: =(Q19-AVERAGE($Q$4:$Q$19))/_xludf.STDEV.S($Q$4:$Q$19) -> #NAME? | AC19: =LN(K19) -> 7.9373747 | AD19: =LN(M19) -> 5.4424177

Sheet 异常检测
A1: 异常检测：在同比序列上使用IQR，不删除真实冲击
A2: 理由：原序列带长期趋势，在水平值上做Z-score会把高增长年份误判为异常；因此以同比变化做IQR检测。|Z|≥3仅作辅助。2020、2022、2023分别对应疫情冲击、再度收缩和恢复反弹，均保留。
A4: 游客量同比Q1 | B4: =(SMALL(预处理结果!S5:S19,4)+SMALL(预处理结果!S5:S19,5))/2 -> 0.056016887 | D4: 收入同比Q1 | E4: =(SMALL(预处理结果!T5:T19,4)+SMALL(预处理结果!T5:T19,5))/2 -> 0.11137124
A5: 游客量同比Q3 | B5: =(SMALL(预处理结果!S5:S19,11)+SMALL(预处理结果!S5:S19,12))/2 -> 0.18516811 | D5: 收入同比Q3 | E5: =(SMALL(预处理结果!T5:T19,11)+SMALL(预处理结果!T5:T19,12))/2 -> 0.23269231
A6: 游客量同比IQR | B6: =B5-B4 -> 0.12915122 | D6: 收入同比IQR | E6: =E5-E4 -> 0.12132107
A7: 游客量下界 | B7: =B4-1.5*B6 -> -0.13770995 | D7: 收入下界 | E7: =E4-1.5*E6 -> -0.070610368
A8: 游客量上界 | B8: =B5+1.5*B6 -> 0.37889494 | D8: 收入上界 | E8: =E5+1.5*E6 -> 0.41467391
A10: 年份 | B10: 游客量同比 | C10: 综合收入同比 | D10: 游客判定 | E10: 收入判定
A11: =预处理结果!A4 -> 2010 | B11: =IF(预处理结果!S4="","",预处理结果!S4) | C11: =IF(预处理结果!T4="","",预处理结果!T4) | D11: =IF(预处理结果!U4="","",预处理结果!U4) | E11: =IF(预处理结果!V4="","",预处理结果!V4)
A12: =预处理结果!A5 -> 2011 | B12: =IF(预处理结果!S5="","",预处理结果!S5) -> 0.29551887 | C12: =IF(预处理结果!T5="","",预处理结果!T5) -> 0.29499998 | D12: =IF(预处理结果!U5="","",预处理结果!U5) -> 正常 | E12: =IF(预处理结果!V5="","",预处理结果!V5) -> 正常
A13: =预处理结果!A6 -> 2012 | B13: =IF(预处理结果!S6="","",预处理结果!S6) -> 0.048607318 | C13: =IF(预处理结果!T6="","",预处理结果!T6) -> 0.13043478 | D13: =IF(预处理结果!U6="","",预处理结果!U6) -> 正常 | E13: =IF(预处理结果!V6="","",预处理结果!V6) -> 正常
A14: =预处理结果!A7 -> 2013 | B14: =IF(预处理结果!S7="","",预处理结果!S7) -> 0.12413194 | C14: =IF(预处理结果!T7="","",预处理结果!T7) -> 0.21538462 | D14: =IF(预处理结果!U7="","",预处理结果!U7) -> 正常 | E14: =IF(预处理结果!V7="","",预处理结果!V7) -> 正常
A15: =预处理结果!A8 -> 2014 | B15: =IF(预处理结果!S8="","",预处理结果!S8) -> 0.19953668 | C15: =IF(预处理结果!T8="","",预处理结果!T8) -> 0.25 | D15: =IF(预处理结果!U8="","",预处理结果!U8) -> 正常 | E15: =IF(预处理结果!V8="","",预处理结果!V8) -> 正常
A16: =预处理结果!A9 -> 2015 | B16: =IF(预处理结果!S9="","",预处理结果!S9) -> 0.17079954 | C16: =IF(预处理结果!T9="","",预处理结果!T9) -> 0.18987342 | D16: =IF(预处理结果!U9="","",预处理结果!U9) -> 正常 | E16: =IF(预处理结果!V9="","",预处理结果!V9) -> 正常
A17: =预处理结果!A10 -> 2016 | B17: =IF(预处理结果!S10="","",预处理结果!S10) -> 0.1469605 | C17: =IF(预处理结果!T10="","",预处理结果!T10) -> 0.16580851 | D17: =IF(预处理结果!U10="","",预处理结果!U10) -> 正常 | E17: =IF(预处理结果!V10="","",预处理结果!V10) -> 正常
A18: =预处理结果!A11 -> 2017 | B18: =IF(预处理结果!S11="","",预处理结果!S11) -> 0.14669223 | C18: =IF(预处理结果!T11="","",预处理结果!T11) -> 0.18628292 | D18: =IF(预处理结果!U11="","",预处理结果!U11) -> 正常 | E18: =IF(预处理结果!V11="","",预处理结果!V11) -> 正常
A19: =预处理结果!A12 -> 2018 | B19: =IF(预处理结果!S12="","",预处理结果!S12) -> 0.11204013 | C19: =IF(预处理结果!T12="","",预处理结果!T12) -> 0.092307692 | D19: =IF(预处理结果!U12="","",预处理结果!U12) -> 正常 | E19: =IF(预处理结果!V12="","",预处理结果!V12) -> 正常
A20: =预处理结果!A13 -> 2019 | B20: =IF(预处理结果!S13="","",预处理结果!S13) -> 0.052631579 | C20: =IF(预处理结果!T13="","",预处理结果!T13) -> 0.16197183 | D20: =IF(预处理结果!U13="","",预处理结果!U13) -> 正常 | E20: =IF(预处理结果!V13="","",预处理结果!V13) -> 正常
A21: =预处理结果!A14 -> 2020 | B21: =IF(预处理结果!S14="","",预处理结果!S14) -> -0.45 | C21: =IF(预处理结果!T14="","",预处理结果!T14) -> -0.505 | D21: =IF(预处理结果!U14="","",预处理结果!U14) -> 保留-结构冲击 | E21: =IF(预处理结果!V14="","",预处理结果!V14) -> 保留-结构冲击
A22: =预处理结果!A15 -> 2021 | B22: =IF(预处理结果!S15="","",预处理结果!S15) -> 0.29146692 | C22: =IF(预处理结果!T15="","",预处理结果!T15) -> 0.34680135 | D22: =IF(预处理结果!U15="","",预处理结果!U15) -> 正常 | E22: =IF(预处理结果!V15="","",预处理结果!V15) -> 正常
... A26: =预处理结果!A19 -> 2025 | B26: =IF(预处理结果!S19="","",预处理结果!S19) -> 0.059402194 | C26: =IF(预处理结果!T19="","",预处理结果!T19) -> 0.045248869 | D26: =IF(预处理结果!U19="","",预处理结果!U19) -> 正常 | E26: =IF(预处理结果!V19="","",预处理结果!V19) -> 正常
A30: 年份 | B30: 游客量同比 | C30: IQR下界 | D30: IQR上界 | F30: 年份 | G30: 综合收入同比 | H30: IQR下界 | I30: IQR上界
A31: =A11 -> 2010 | B31: =B11 | C31: =$B$7 -> -0.13770995 | D31: =$B$8 -> 0.37889494 | F31: =A11 -> 2010 | G31: =C11 | H31: =$E$7 -> -0.070610368 | I31: =$E$8 -> 0.41467391
A32: =A12 -> 2011 | B32: =B12 -> 0.29551887 | C32: =$B$7 -> -0.13770995 | D32: =$B$8 -> 0.37889494 | F32: =A12 -> 2011 | G32: =C12 -> 0.29499998 | H32: =$E$7 -> -0.070610368 | I32: =$E$8 -> 0.41467391
A33: =A13 -> 2012 | B33: =B13 -> 0.048607318 | C33: =$B$7 -> -0.13770995 | D33: =$B$8 -> 0.37889494 | F33: =A13 -> 2012 | G33: =C13 -> 0.13043478 | H33: =$E$7 -> -0.070610368 | I33: =$E$8 -> 0.41467391
A34: =A14 -> 2013 | B34: =B14 -> 0.12413194 | C34: =$B$7 -> -0.13770995 | D34: =$B$8 -> 0.37889494 | F34: =A14 -> 2013 | G34: =C14 -> 0.21538462 | H34: =$E$7 -> -0.070610368 | I34: =$E$8 -> 0.41467391
A35: =A15 -> 2014 | B35: =B15 -> 0.19953668 | C35: =$B$7 -> -0.13770995 | D35: =$B$8 -> 0.37889494 | F35: =A15 -> 2014 | G35: =C15 -> 0.25 | H35: =$E$7 -> -0.070610368 | I35: =$E$8 -> 0.41467391
A36: =A16 -> 2015 | B36: =B16 -> 0.17079954 | C36: =$B$7 -> -0.13770995 | D36: =$B$8 -> 0.37889494 | F36: =A16 -> 2015 | G36: =C16 -> 0.18987342 | H36: =$E$7 -> -0.070610368 | I36: =$E$8 -> 0.41467391
A37: =A17 -> 2016 | B37: =B17 -> 0.1469605 | C37: =$B$7 -> -0.13770995 | D37: =$B$8 -> 0.37889494 | F37: =A17 -> 2016 | G37: =C17 -> 0.16580851 | H37: =$E$7 -> -0.070610368 | I37: =$E$8 -> 0.41467391
A38: =A18 -> 2017 | B38: =B18 -> 0.14669223 | C38: =$B$7 -> -0.13770995 | D38: =$B$8 -> 0.37889494 | F38: =A18 -> 2017 | G38: =C18 -> 0.18628292 | H38: =$E$7 -> -0.070610368 | I38: =$E$8 -> 0.41467391
A39: =A19 -> 2018 | B39: =B19 -> 0.11204013 | C39: =$B$7 -> -0.13770995 | D39: =$B$8 -> 0.37889494 | F39: =A19 -> 2018 | G39: =C19 -> 0.092307692 | H39: =$E$7 -> -0.070610368 | I39: =$E$8 -> 0.41467391
A40: =A20 -> 2019 | B40: =B20 -> 0.052631579 | C40: =$B$7 -> -0.13770995 | D40: =$B$8 -> 0.37889494 | F40: =A20 -> 2019 | G40: =C20 -> 0.16197183 | H40: =$E$7 -> -0.070610368 | I40: =$E$8 -> 0.41467391
A41: =A21 -> 2020 | B41: =B21 -> -0.45 | C41: =$B$7 -> -0.13770995 | D41: =$B$8 -> 0.37889494 | F41: =A21 -> 2020 | G41: =C21 -> -0.505 | H41: =$E$7 -> -0.070610368 | I41: =$E$8 -> 0.41467391
A42: =A22 -> 2021 | B42: =B22 -> 0.29146692 | C42: =$B$7 -> -0.13770995 | D42: =$B$8 -> 0.37889494 | F42: =A22 -> 2021 | G42: =C22 -> 0.34680135 | H42: =$E$7 -> -0.070610368 | I42: =$E$8 -> 0.41467391
... A46: =A26 -> 2025 | B46: =B26 -> 0.059402194 | C46: =$B$7 -> -0.13770995 | D46: =$B$8 -> 0.37889494 | F46: =A26 -> 2025 | G46: =C26 -> 0.045248869 | H46: =$E$7 -> -0.070610368 | I46: =$E$8 -> 0.41467391

Sheet 趋势图
A1: 原始序列与清洗序列对照
A2: 图中原始序列保留缺口；清洗序列使用补充假设补全。2020—2022的变化不做平滑删除，正式模型必须加入疫情/恢复状态。
A4: 年份 | B4: 游客原始 | C4: 游客清洗 | D4: 收入原始 | E4: 收入清洗
A5: =预处理结果!A4 -> 2010 | B5: =IF(预处理结果!B4="","",预处理结果!B4) -> 848 | C5: =预处理结果!K4 -> 848 | D5: =IF(预处理结果!D4="","",预处理结果!D4) -> 35.521236 | E5: =预处理结果!M4 -> 35.521236
A6: =预处理结果!A5 -> 2011 | B6: =IF(预处理结果!B5="","",预处理结果!B5) -> 1098.6 | C6: =预处理结果!K5 -> 1098.6 | D6: =IF(预处理结果!D5="","",预处理结果!D5) -> 46 | E6: =预处理结果!M5 -> 46
A7: =预处理结果!A6 -> 2012 | B7: =IF(预处理结果!B6="","",预处理结果!B6) -> 1152 | C7: =预处理结果!K6 -> 1152 | D7: =IF(预处理结果!D6="","",预处理结果!D6) -> 52 | E7: =预处理结果!M6 -> 52
A8: =预处理结果!A7 -> 2013 | B8: =IF(预处理结果!B7="","",预处理结果!B7) -> 1295 | C8: =预处理结果!K7 -> 1295 | D8: =IF(预处理结果!D7="","",预处理结果!D7) -> 63.2 | E8: =预处理结果!M7 -> 63.2
A9: =预处理结果!A8 -> 2014 | B9: =IF(预处理结果!B8="","",预处理结果!B8) -> 1553.4 | C9: =预处理结果!K8 -> 1553.4 | D9: =IF(预处理结果!D8="","",预处理结果!D8) -> 79 | E9: =预处理结果!M8 -> 79
A10: =预处理结果!A9 -> 2015 | B10: =IF(预处理结果!B9="","",预处理结果!B9) -> 1818.72 | C10: =预处理结果!K9 -> 1818.72 | D10: =IF(预处理结果!D9="","",预处理结果!D9) -> 94 | E10: =预处理结果!M9 -> 94
A11: =预处理结果!A10 -> 2016 | B11: =IF(预处理结果!B10="","",预处理结果!B10) -> 2086 | C11: =预处理结果!K10 -> 2086 | D11: =IF(预处理结果!D10="","",预处理结果!D10) | E11: =预处理结果!M10 -> 109.586
A12: =预处理结果!A11 -> 2017 | B12: =IF(预处理结果!B11="","",预处理结果!B11) -> 2392 | C12: =预处理结果!K11 -> 2392 | D12: =IF(预处理结果!D11="","",预处理结果!D11) -> 130 | E12: =预处理结果!M11 -> 130
A13: =预处理结果!A12 -> 2018 | B13: =IF(预处理结果!B12="","",预处理结果!B12) -> 2660 | C13: =预处理结果!K12 -> 2660 | D13: =IF(预处理结果!D12="","",预处理结果!D12) -> 142 | E13: =预处理结果!M12 -> 142
A14: =预处理结果!A13 -> 2019 | B14: =IF(预处理结果!B13="","",预处理结果!B13) -> 2800 | C14: =预处理结果!K13 -> 2800 | D14: =IF(预处理结果!D13="","",预处理结果!D13) -> 165 | E14: =预处理结果!M13 -> 165
A15: =预处理结果!A14 -> 2020 | B15: =IF(预处理结果!B14="","",预处理结果!B14) | C15: =预处理结果!K14 -> 1540 | D15: =IF(预处理结果!D14="","",预处理结果!D14) | E15: =预处理结果!M14 -> 81.675
A16: =预处理结果!A15 -> 2021 | B16: =IF(预处理结果!B15="","",预处理结果!B15) | C16: =预处理结果!K15 -> 1988.8591 | D16: =IF(预处理结果!D15="","",预处理结果!D15) -> 110 | E16: =预处理结果!M15 -> 110
... A20: =预处理结果!A19 -> 2025 | B20: =IF(预处理结果!B19="","",预处理结果!B19) | C20: =预处理结果!K19 -> 2800 | D20: =IF(预处理结果!D19="","",预处理结果!D19) | E20: =预处理结果!M19 -> 231

Sheet 数据补充
A1: 必须补充、可选补充与相关指标覆盖
A2: 原则：必须补充决定模型是否可识别；可选补充只在能够稳定提高样本外预测时纳入。无官方依据的数据不生成伪精确值，必要时使用区间或标准化指数。
A4: 类别 | B4: 变量/缺口 | C4: 当前状态 | D4: 为什么需要 | E4: 推荐获取途径 | F4: 本轮生成假设 | G4: 不确定性处理
A5: 必须补充 | B5: 2020、2022、2025年度游客量与综合收入；2021游客量 | C5: 年度实际值缺失；仅有2021—2025累计值、2025目标值及部分年度收入 | D5: 两项核心因变量必须形成连续序列，且疫情冲击幅度直接影响趋势与预测区间 | E5: 蓟州区政府工作报告/统计公报原件、区文旅局年度总结、天津市文旅局；优先申请内部统计表 | F5: 用五年累计约束、2025目标替代值和2021/2022收入比例分配游客余量；所有结果标记为假设补全 | G5: 对2025目标替代值做±5%至±10%敏感性分析，并重新分配2021—2022余量
A6: 必须补充 | B6: 2016年同口径旅游综合收入 | C6: 仅有旅游直接收入21.9172亿元 | D6: 疫情前趋势模型需要连续收入序列 | E6: 2017年政府工作报告附件、蓟州区文旅局、后续统计表回列值 | F6: 按2011、2013—2015、2017年综合收入/直接收入约5倍的稳定关系桥接为109.586亿元 | G6: 桥接倍数在4.8—5.2之间扰动
A7: 必须补充 | B7: 旅游收入价格平减指数 | C7: 现有收入均为当年价，未形成实际收入 | D7: 名义价格上涨会夸大旅游经济真实增长 | E7: 国家统计局/天津统计局CPI，优先住宿、餐饮、交通、文娱分项构造旅游价格指数 | F7: 当前工作簿暂保留名义收入；正式建模前以2025年为100进行平减 | G7: 比较综合CPI与旅游分项加权指数两种口径
A8: 必须补充 | B8: 2026—2030政策投入、客源市场和新业态情景参数 | C8: 现有财政功能分类支出不等于旅游专项投入，未来值未给出 | D8: 问题3三情景和量化建议必须有可调参数 | E8: 蓟州区“十五五”规划、财政预算、文旅项目清单、京津冀协同文件；必要时专家打分 | F8: 标准化为基准1.00的指数，乐观/悲观区间由规划目标与历史波动共同设定 | G8: 使用三角分布或PERT分布，报告5%、50%、95%分位数
A9: 可选补充 | B9: 京津客源占比、移动/高速交通流量、搜索热度 | C9: 现有表中没有年度客源结构与高频需求先行指标 | D9: 可提升客流预测的及时性并解释区域协同效应 | E9: 景区票务与运营商脱敏数据、交通运输部门、高速出入口流量、百度指数/微信指数 | F9: 未生成具体数值，避免用无依据的网络热度替代官方客流 | G9: 先做相关性与滞后检验，再决定是否纳入
A10: 可选补充 | B10: 住宿供给、入住率、重点景区接待量、节假日与天气 | C10: 仅有天津市级星级饭店与A级景区结构校验数据 | D10: 可解释人均消费、新业态供给和季节/节假日波动 | E10: 天津市文旅局、蓟州区文旅局、气象局、酒店协会及重点景区运营数据 | F10: 若无法获得，仅作为情景解释变量，不强行生成年度观测 | G10: 采用区间或等级变量，避免伪造精确值
A13: 现有相关指标覆盖（只用于筛选，不代表可直接进入模型）
A14: 指标 | B14: 单位 | C14: 观测数 | D14: 起始年 | E14: 结束年
A15: all_resident_disposable_income | B15: cny_per_person | C15: 8 | D15: 2017 | E15: 2025
A16: culture_tourism_sports_media_expenditure | B16: 10k_cny | C16: 3 | D16: 2022 | E16: 2024
A17: fixed_asset_investment | B17: 100m_cny | C17: 4 | D17: 2014 | E17: 2017
A18: general_public_budget_expenditure | B18: 100m_cny | C18: 6 | D18: 2020 | E18: 2025
A19: permanent_population | B19: 10k_persons | C19: 1 | D19: 2019 | E19: 2019
A20: road_mileage | B20: km | C20: 1 | D20: 2019 | E20: 2019
A21: rural_disposable_income | B21: cny_per_person | C21: 2 | D21: 2016 | E21: 2017
A22: social_retail_sales | B22: 100m_cny | C22: 9 | D22: 2014 | E22: 2025
A23: social_retail_sales_yoy | B23: percent | C23: 1 | D23: 2020 | E23: 2020
A24: urban_disposable_income | B24: cny_per_person | C24: 2 | D24: 2016 | E24: 2017
